django_survey_and_report-1.4.11.dist-info/licenses/LICENSE.txt
survey/__init__.py
survey/actions.py
survey/admin.py
survey/apps.py
survey/decorators.py
survey/forms.py
survey/runtests.py
survey/settings.py
survey/signals.py
survey/urls.py
survey/widgets.py
survey/exporter/__init__.py
survey/exporter/survey2x.py
survey/exporter/csv/__init__.py
survey/exporter/csv/survey2csv.py
survey/exporter/tex/__init__.py
survey/exporter/tex/configuration.py
survey/exporter/tex/configuration_builder.py
survey/exporter/tex/default_conf.yaml
survey/exporter/tex/latex_file.py
survey/exporter/tex/question2tex.py
survey/exporter/tex/question2tex_chart.py
survey/exporter/tex/question2tex_raw.py
survey/exporter/tex/question2tex_sankey.py
survey/exporter/tex/survey2tex.py
survey/locale/de/LC_MESSAGES/django.po
survey/locale/es/LC_MESSAGES/django.po
survey/locale/fr/LC_MESSAGES/django.po
survey/locale/gr/LC_MESSAGES/django.po
survey/locale/id/LC_MESSAGES/django.po
survey/locale/ja/LC_MESSAGES/django.po
survey/locale/nl/LC_MESSAGES/django.po
survey/locale/pl/LC_MESSAGES/django.po
survey/locale/pt/LC_MESSAGES/django.po
survey/locale/ru/LC_MESSAGES/django.po
survey/locale/tr/LC_MESSAGES/django.po
survey/locale/zh/LC_MESSAGES/django.po
survey/management/__init__.py
survey/management/survey_command.py
survey/management/commands/__init__.py
survey/management/commands/exportresult.py
survey/management/commands/generatetexconf.py
survey/migrations/0001_initial.py
survey/migrations/0002_survey_template.py
survey/migrations/0003_auto_20170320_0337.py
survey/migrations/0004_polymorphic_answers_to_kiss.py
survey/migrations/0005_rename_question_related_name.py
survey/migrations/0006_add_related_name_for_categories.py
survey/migrations/0007_auto_20180217_1515.py
survey/migrations/0008_translated_name_for_models.py
survey/migrations/0009_auto_20181211_1908.py
survey/migrations/0010_survey_editable_answers.py
survey/migrations/0011_survey_publish_duration.py
survey/migrations/0012_add_display_by_category.py
survey/migrations/0013_auto_20200609_0748.py
django_survey_and_report-1.4.11.dist-info/METADATA
django_survey_and_report-1.4.11.dist-info/WHEEL
django_survey_and_report-1.4.11.dist-info/top_level.txt
django_survey_and_report-1.4.11.dist-info/RECORD
