Metadata-Version: 2.4
Name: django-survey-and-report
Version: 1.4.11
Summary: A django survey app that can export results as CSV or PDF using your native language.
Author-email: Pierre SASSOULAS <pierre.sassoulas@gmail.com>
License: AGPL-3.0
Project-URL: Bug Tracker, https://github.com/Pierre-Sassoulas/django-survey/issues
Project-URL: Source Code, https://github.com/Pierre-Sassoulas/django-survey
Classifier: Development Status :: 5 - Production/Stable
Classifier: Environment :: Web Environment
Classifier: Framework :: Django
Classifier: Intended Audience :: Developers
Classifier: License :: OSI Approved :: GNU Affero General Public License v3
Classifier: Natural Language :: Chinese (Traditional)
Classifier: Natural Language :: Dutch
Classifier: Natural Language :: English
Classifier: Natural Language :: French
Classifier: Natural Language :: German
Classifier: Natural Language :: Indonesian
Classifier: Natural Language :: Japanese
Classifier: Natural Language :: Polish
Classifier: Natural Language :: Portuguese
Classifier: Natural Language :: Russian
Classifier: Natural Language :: Spanish
Classifier: Operating System :: OS Independent
Classifier: Programming Language :: Python :: 3 :: Only
Classifier: Programming Language :: Python :: 3.9
Classifier: Programming Language :: Python :: 3.10
Classifier: Programming Language :: Python :: 3.11
Classifier: Programming Language :: Python :: 3.12
Classifier: Programming Language :: Python :: 3.13
Classifier: Programming Language :: Python :: 3.14
Classifier: Topic :: Utilities
Requires-Python: >=3.9
License-File: LICENSE.txt
Requires-Dist: django<6,>=2.2
Requires-Dist: pytz>=2018.9
Requires-Dist: pyyaml>=4.2b1
Provides-Extra: dev
Requires-Dist: colorama; extra == "dev"
Requires-Dist: coverage; extra == "dev"
Requires-Dist: coveralls; extra == "dev"
Requires-Dist: django-rosetta; extra == "dev"
Requires-Dist: pre-commit; extra == "dev"
Requires-Dist: pylint>=3.3.5; extra == "dev"
Requires-Dist: pylint-django; extra == "dev"
Requires-Dist: pysankeybeta<1.5,>=1.3; extra == "dev"
Requires-Dist: pytest; extra == "dev"
Requires-Dist: pytest-django; extra == "dev"
Requires-Dist: python-coveralls; extra == "dev"
Requires-Dist: setuptools; extra == "dev"
Provides-Extra: sankey
Requires-Dist: pysankeybeta<1.5,>=1.3; extra == "sankey"
Dynamic: license-file
